aiosellers/__init__.py
aiosellers/playerok/__init__.py
aiosellers/playerok/client_config.py
aiosellers/playerok/graphql.py
aiosellers/playerok/playerok.py
aiosellers/playerok/api/__init__.py
aiosellers/playerok/api/account.py
aiosellers/playerok/api/chats.py
aiosellers/playerok/api/deals.py
aiosellers/playerok/api/games.py
aiosellers/playerok/api/items.py
aiosellers/playerok/core/__init__.py
aiosellers/playerok/core/config.py
aiosellers/playerok/core/constants.py
aiosellers/playerok/core/exceptions.py
aiosellers/playerok/core/identity_map.py
aiosellers/playerok/core/pagination.py
aiosellers/playerok/core/types.py
aiosellers/playerok/core/utils.py
aiosellers/playerok/entities/__init__.py
aiosellers/playerok/entities/chat.py
aiosellers/playerok/entities/deal.py
aiosellers/playerok/entities/file.py
aiosellers/playerok/entities/game.py
aiosellers/playerok/entities/item.py
aiosellers/playerok/entities/user.py
aiosellers/playerok/raw/__init__.py
aiosellers/playerok/raw/account.py
aiosellers/playerok/raw/chats.py
aiosellers/playerok/raw/deals.py
aiosellers/playerok/raw/games.py
aiosellers/playerok/raw/items.py
aiosellers/playerok/raw/transactions.py
aiosellers/playerok/schemas/__init__.py
aiosellers/playerok/schemas/account.py
aiosellers/playerok/schemas/basic.py
aiosellers/playerok/schemas/chats.py
aiosellers/playerok/schemas/deals.py
aiosellers/playerok/schemas/enums.py
aiosellers/playerok/schemas/games.py
aiosellers/playerok/schemas/items.py
aiosellers/playerok/schemas/transactions.py
aiosellers/playerok/transport/__init__.py
aiosellers/playerok/transport/tls.py
aiosellers-0.1.2.dist-info/licenses/LICENSE
aiosellers-0.1.2.dist-info/METADATA
aiosellers-0.1.2.dist-info/WHEEL
aiosellers-0.1.2.dist-info/top_level.txt
aiosellers-0.1.2.dist-info/RECORD
