Metadata-Version: 2.4
Name: aiosellers
Version: 0.1.2
Summary: All In One Sellers API - Universal API for various digital trading platforms (such as PlayerOK or FunPay). Provides developers with a convenient way to create bots on any platform.
Requires-Python: >=3.12
License-File: LICENSE
Requires-Dist: idna>=3.11
Requires-Dist: pydantic>=2.12.5
Requires-Dist: python-dotenv>=1.2.1
Requires-Dist: ruff>=0.14.10
Requires-Dist: wrapper-tls-requests>=1.1.9
Dynamic: license-file
